geography/__init__.py
geography/countryDict.py
geography-0.0.74.dist-info/LICENSE.txt
geography-0.0.74.dist-info/METADATA
geography-0.0.74.dist-info/WHEEL
geography-0.0.74.dist-info/top_level.txt
geography-0.0.74.dist-info/RECORD
