Metadata-Version: 2.1
Name: geography
Version: 0.0.74
Summary: Get info about countries and states
Home-page: 
Author: FrenchFries8854
Author-email: frenchfries8854@gmail.com
License: MIT
Keywords: geography
Classifier: Development Status :: 5 - Production/Stable
Classifier: Intended Audience :: Developers
Classifier: Operating System :: Microsoft :: Windows :: Windows 10
Classifier: License :: OSI Approved :: MIT License
Classifier: Programming Language :: Python :: 3
License-File: LICENSE.txt
